genrex/__init__.py
genrex/pattern.py
genrex/util.py
genrex-1.0.1.dist-info/LICENSE
genrex-1.0.1.dist-info/METADATA
genrex-1.0.1.dist-info/WHEEL
genrex-1.0.1.dist-info/top_level.txt
genrex-1.0.1.dist-info/RECORD
