Metadata-Version: 2.1
Name: genrex
Version: 1.0.1
Summary: Genrex generates matching strings to a given regular expressions.
Home-page: https://github.com/abichinger/genrex
Author: abichinger
Author-email: abichinger@example.com
License: MIT
Platform: UNKNOWN
Classifier: Programming Language :: Python :: 3
Classifier: License :: OSI Approved :: MIT License
Classifier: Operating System :: OS Independent
Requires-Python: >=3.3
